CHANGES.md
MANIFEST.in
README.md
setup.py
onetable/__init__.py
onetable.egg-info/PKG-INFO
onetable.egg-info/SOURCES.txt
onetable.egg-info/dependency_links.txt
onetable.egg-info/not-zip-safe
onetable.egg-info/top_level.txt