Metadata-Version: 2.1
Name: onetable
Version: 0.0.5
Summary: Once defined, multiple ways to export table.
Home-page: https://github.com/sintrb/onetable/
Author: trb
Author-email: sintrb@gmail.com
License: UNKNOWN
Keywords: onetable,excel,csv,table,export
Platform: UNKNOWN
